tt_sim/__init__.py
tt_sim/core/bike.py
tt_sim/core/critical_power.py
tt_sim/core/rider.py
tt_sim/core/simulation.py
tt_sim/core/stage.py
tt_sim/core/wind.py
tt_sim-0.0.0.post7.dist-info/LICENSE
tt_sim-0.0.0.post7.dist-info/WHEEL
tt_sim-0.0.0.post7.dist-info/METADATA
tt_sim-0.0.0.post7.dist-info/RECORD
