Metadata-Version: 2.1
Name: tt-sim
Version: 0.0.0.post7
Summary: Time Trial Simulator
Author: Jim Parr
Author-email: jimparr19@gmail.com
Requires-Python: >=3.7.1,<3.10
Classifier: Programming Language :: Python :: 3
Classifier: Programming Language :: Python :: 3.8
Classifier: Programming Language :: Python :: 3.9
Requires-Dist: geographiclib (>=1.52,<2.0)
Requires-Dist: pandas (>=1.3.3,<2.0.0)
Requires-Dist: scipy (>=1.7.1,<2.0.0)
